pydralion/__init__.py
pydralion/base_api.py
pydralion/check_type.py
pydralion/crypt.py
pydralion/etcd_conf.py
pydralion/json_encode.py
pydralion/log_init.py
pydralion/pycas.py
pydralion/redis_db.py
pydralion/request_url.py
pydralion/socket_ip.py
pydralion/sql_db.py
pydralion/utils.py
pydralion/zk_db.py
pydralion-0.0.1.dist-info/METADATA
pydralion-0.0.1.dist-info/WHEEL
pydralion-0.0.1.dist-info/top_level.txt
pydralion-0.0.1.dist-info/RECORD
