Metadata-Version: 2.1
Name: pydralion
Version: 0.0.1
Summary: this is a pydralion utils package
Home-page: http://iop.sf-express.com/auth
Author: zhaokai5520
Author-email: zhaokai5520@foxmail.com
License: MIT
Platform: UNKNOWN
Classifier: Environment :: Web Environment
Classifier: Intended Audience :: Developers
Classifier: Operating System :: OS Independent
Classifier: Topic :: Text Processing :: Indexing
Classifier: Topic :: Utilities
Classifier: Topic :: Internet
Classifier: Topic :: Software Development :: Libraries :: Python Modules
Classifier: Programming Language :: Python
Classifier: Programming Language :: Python :: 3.6
